{"version":1,"set_title":"Justice League Strategy Game","001":{"team_ability":["Justice League","Superman Ally"],"keywords":"Celebrity, Justice League, Kryptonian, Metropolis, Reporter","name":"Superman","points":"200|100"},"002":{"team_ability":["Batman Ally","Justice League"],"keywords":"Batman Family, Detective, Gotham City, Justice League, Martial Artist","name":"Batman","points":"150|100"},"003":{"team_ability":["Justice League"],"keywords":"Amazon, Justice League, Warrior","name":"Wonder Woman","points":"150|100"},"004":{"team_ability":["Justice League"],"keywords":"Justice League, Robot","name":"Cyborg","points":"100"},"005":{"team_ability":["Quintessence"],"keywords":"Apokolips, Ruler","name":"Darkseid","points":"400|300"},"B001":{"name":"Parademon","points":"10"}}